mechwolf
