Metadata-Version: 2.1
Name: mechwolf
Version: 0.1.1
Summary: Continuous flow process description, analysis, and automation
Home-page: https://github.com/MechWolf/MechWolf
Author: Benjamin Lee and Alex Mijalis
Author-email: benjamindlee@me.com
License: UNKNOWN
Platform: UNKNOWN
Classifier: Development Status :: 3 - Alpha
Classifier: Intended Audience :: Developers
Classifier: Intended Audience :: Healthcare Industry
Classifier: Intended Audience :: Manufacturing
Classifier: Intended Audience :: Science/Research
Classifier: Programming Language :: Python :: 3.7
Classifier: Topic :: Scientific/Engineering :: Chemistry
Requires-Python: >=3.7
